setup.py
sconsduino/__init__.py
sconsduino/avr.py
sconsduino/nanopb.py
sconsduino/teensy.py
sconsduino.egg-info/PKG-INFO
sconsduino.egg-info/SOURCES.txt
sconsduino.egg-info/dependency_links.txt
sconsduino.egg-info/top_level.txt
sconsduino/arduino/__init__.py
sconsduino/arduino/promini.py